{
	"name": "Layout 1",
	"layers": [
		{
			"name": "Layer 0",
			"overriden": 0,
			"subLayers": [],
			"instances": [
				{
					"type": "TiledBackground2",
					"properties": {
						"initially-visible": true,
						"origin": "top-left",
						"wrap-horizontal": "repeat",
						"wrap-vertical": "repeat",
						"image-offset-x": 0,
						"image-offset-y": 0,
						"image-scale-x": 1,
						"image-scale-y": 1,
						"image-angle": 0
					},
					"uid": 3,
					"instanceVariables": {},
					"behaviors": {},
					"world": {
						"x": 0,
						"y": 0,
						"width": 1708,
						"height": 960,
						"originX": 0,
						"originY": 0,
						"color": [
							1,
							1,
							1,
							1
						],
						"angle": 0,
						"zElevation": 0
					}
				},
				{
					"type": "Sprite",
					"properties": {
						"initially-visible": true,
						"initial-animation": "Animation 1",
						"initial-frame": 0,
						"enable-collisions": true,
						"live-preview": false
					},
					"uid": 4,
					"instanceVariables": {},
					"behaviors": {
						"Solid": {
							"properties": {
								"enabled": true,
								"tags": ""
							}
						}
					},
					"world": {
						"x": 861,
						"y": 917,
						"width": 1697,
						"height": 79,
						"originX": 0.5,
						"originY": 0.5,
						"color": [
							1,
							1,
							1,
							1
						],
						"angle": 0,
						"zElevation": 0
					}
				},
				{
					"type": "TiledBackground3",
					"properties": {
						"initially-visible": true,
						"origin": "top-left",
						"wrap-horizontal": "repeat",
						"wrap-vertical": "repeat",
						"image-offset-x": 0,
						"image-offset-y": 0,
						"image-scale-x": 1,
						"image-scale-y": 1,
						"image-angle": 0
					},
					"uid": 6,
					"instanceVariables": {},
					"behaviors": {},
					"world": {
						"x": 116,
						"y": 446,
						"width": 100,
						"height": 100,
						"originX": 0,
						"originY": 0,
						"color": [
							1,
							1,
							1,
							1
						],
						"angle": 0,
						"zElevation": 0
					}
				},
				{
					"type": "bullet",
					"properties": {
						"initially-visible": true,
						"initial-animation": "Animation 1",
						"initial-frame": 0,
						"enable-collisions": true,
						"live-preview": false
					},
					"uid": 7,
					"instanceVariables": {},
					"behaviors": {
						"Bullet": {
							"properties": {
								"speed": 600,
								"acceleration": 0,
								"gravity": 0,
								"bounce-off-solids": false,
								"set-angle": true,
								"step": false,
								"enabled": true
							}
						}
					},
					"world": {
						"x": 422,
						"y": -30,
						"width": 37.92,
						"height": 20.328,
						"originX": 0.43037974683544306,
						"originY": 0.5238095238095238,
						"color": [
							1,
							1,
							1,
							1
						],
						"angle": 0,
						"zElevation": 0
					}
				},
				{
					"type": "enemy",
					"properties": {
						"initially-visible": true,
						"initial-animation": "Animation 1",
						"initial-frame": 0,
						"enable-collisions": true,
						"live-preview": false
					},
					"uid": 29,
					"instanceVariables": {
						"Heath": 50
					},
					"behaviors": {
						"LineOfSight": {
							"properties": {
								"obstacles": "solids",
								"range": 600,
								"cone-of-view": 360,
								"use-collision-cells": true
							}
						},
						"Flash": {
							"properties": {}
						},
						"ScrollTo": {
							"properties": {
								"enabled": true
							}
						}
					},
					"world": {
						"x": 1129,
						"y": 738,
						"width": -128.78201576280225,
						"height": 127.88000000000001,
						"originX": 0.5,
						"originY": 0.5,
						"color": [
							1,
							1,
							1,
							1
						],
						"angle": 6.273411109595479,
						"zElevation": 0
					}
				},
				{
					"type": "Sprite3",
					"properties": {
						"initially-visible": true,
						"initial-animation": "Animation 1",
						"initial-frame": 0,
						"enable-collisions": true,
						"live-preview": false
					},
					"uid": 30,
					"instanceVariables": {},
					"behaviors": {
						"Bullet": {
							"properties": {
								"speed": 400,
								"acceleration": 0,
								"gravity": 0,
								"bounce-off-solids": false,
								"set-angle": true,
								"step": false,
								"enabled": true
							}
						}
					},
					"world": {
						"x": 697,
						"y": -37,
						"width": 50,
						"height": 50,
						"originX": 0.404,
						"originY": 0.452,
						"color": [
							1,
							1,
							1,
							1
						],
						"angle": 0,
						"zElevation": 0
					}
				},
				{
					"type": "Sprite4",
					"properties": {
						"initially-visible": true,
						"initial-animation": "Animation 1",
						"initial-frame": 0,
						"enable-collisions": true,
						"live-preview": false
					},
					"uid": 5,
					"instanceVariables": {},
					"behaviors": {
						"ScrollTo": {
							"properties": {
								"enabled": true
							}
						},
						"Platform": {
							"properties": {
								"max-speed": 330,
								"acceleration": 1500,
								"deceleration": 1500,
								"jump-strength": 650,
								"gravity": 1500,
								"max-fall-speed": 1000,
								"double-jump": false,
								"jump-sustain": 0,
								"default-controls": false,
								"enabled": true
							}
						},
						"Flash": {
							"properties": {}
						},
						"Physics": {
							"properties": {
								"immovable": false,
								"collision-mask": "use-collision-polygon",
								"prevent-rotation": false,
								"density": 1,
								"friction": 0.5,
								"elasticity": 0.2,
								"linear-damping": 0,
								"angular-damping": 0.01,
								"bullet": false,
								"enabled": true
							}
						}
					},
					"world": {
						"x": 399,
						"y": 695,
						"width": 62,
						"height": 60,
						"originX": 0.5,
						"originY": 0.5,
						"color": [
							1,
							1,
							1,
							1
						],
						"angle": 0.021176237876927573,
						"zElevation": 0
					}
				},
				{
					"type": "groundSoild",
					"properties": {
						"initially-visible": true,
						"initial-animation": "Animation 1",
						"initial-frame": 0,
						"enable-collisions": true,
						"live-preview": false
					},
					"uid": 10,
					"instanceVariables": {},
					"behaviors": {
						"Solid": {
							"properties": {
								"enabled": true,
								"tags": ""
							}
						}
					},
					"world": {
						"x": 625,
						"y": 753,
						"width": 539,
						"height": 56,
						"originX": 0.5264270613107822,
						"originY": -1.25,
						"color": [
							1,
							1,
							1,
							1
						],
						"angle": 0,
						"zElevation": 0
					}
				},
				{
					"type": "groundSoild",
					"properties": {
						"initially-visible": true,
						"initial-animation": "Animation 1",
						"initial-frame": 0,
						"enable-collisions": true,
						"live-preview": false
					},
					"uid": 11,
					"instanceVariables": {},
					"behaviors": {
						"Solid": {
							"properties": {
								"enabled": true,
								"tags": ""
							}
						}
					},
					"world": {
						"x": 1120,
						"y": 714,
						"width": 454,
						"height": 74,
						"originX": 0.5264270613107822,
						"originY": -1.25,
						"color": [
							1,
							1,
							1,
							1
						],
						"angle": 0,
						"zElevation": 0
					}
				},
				{
					"type": "gun",
					"properties": {
						"initially-visible": true,
						"initial-animation": "Animation 1",
						"initial-frame": 0,
						"enable-collisions": true,
						"live-preview": false
					},
					"uid": 12,
					"instanceVariables": {},
					"behaviors": {
						"LineOfSight": {
							"properties": {
								"obstacles": "solids",
								"range": 600,
								"cone-of-view": 360,
								"use-collision-cells": true
							}
						}
					},
					"world": {
						"x": 1073,
						"y": 734,
						"width": -102,
						"height": 65,
						"originX": 0.5575221238938053,
						"originY": 0.6906474820143884,
						"color": [
							1,
							1,
							1,
							1
						],
						"angle": 3.114599040808029,
						"zElevation": 0
					}
				},
				{
					"type": "TiledBackground5",
					"properties": {
						"initially-visible": true,
						"origin": "top-left",
						"wrap-horizontal": "repeat",
						"wrap-vertical": "repeat",
						"image-offset-x": 0,
						"image-offset-y": 0,
						"image-scale-x": 1,
						"image-scale-y": 1,
						"image-angle": 0
					},
					"uid": 2,
					"instanceVariables": {},
					"behaviors": {},
					"world": {
						"x": 53,
						"y": 389,
						"width": 1681,
						"height": 208,
						"originX": 0,
						"originY": 0,
						"color": [
							1,
							1,
							1,
							1
						],
						"angle": 0,
						"zElevation": 0
					}
				},
				{
					"type": "currentHeathBG",
					"properties": {
						"initially-visible": true,
						"initial-animation": "Animation 1",
						"initial-frame": 0,
						"enable-collisions": true,
						"live-preview": false
					},
					"uid": 13,
					"instanceVariables": {},
					"behaviors": {},
					"world": {
						"x": 1028.9368109886082,
						"y": 622.6947290550553,
						"width": 208,
						"height": 18,
						"originX": 0,
						"originY": 0.5,
						"color": [
							1,
							1,
							1,
							1
						],
						"angle": 0,
						"zElevation": 0
					}
				},
				{
					"type": "currentHeathBG2",
					"properties": {
						"initially-visible": true,
						"initial-animation": "Animation 1",
						"initial-frame": 0,
						"enable-collisions": true,
						"live-preview": false
					},
					"uid": 14,
					"instanceVariables": {},
					"behaviors": {},
					"world": {
						"x": 1028.6849482771077,
						"y": 622.767808343811,
						"width": 208,
						"height": 18,
						"originX": 0,
						"originY": 0.5,
						"color": [
							1,
							1,
							1,
							1
						],
						"angle": 0,
						"zElevation": 0
					}
				},
				{
					"type": "controlBar",
					"properties": {
						"initially-visible": true,
						"initial-animation": "Animation 1",
						"initial-frame": 0,
						"enable-collisions": true,
						"live-preview": false
					},
					"uid": 9,
					"instanceVariables": {
						"restBar": true
					},
					"behaviors": {
						"Pin": {
							"properties": {
								"destroy": false
							}
						}
					},
					"world": {
						"x": 310,
						"y": 796,
						"width": 188,
						"height": 32,
						"originX": 0,
						"originY": 0.5,
						"color": [
							1,
							1,
							1,
							1
						],
						"angle": 0,
						"zElevation": 0
					}
				},
				{
					"type": "Text",
					"properties": {
						"text": "Text",
						"enable-bbcode": true,
						"font": "Arial",
						"size": 12,
						"line-height": 0,
						"bold": false,
						"italic": false,
						"color": [
							0,
							0,
							0,
							1
						],
						"horizontal-alignment": "left",
						"vertical-alignment": "top",
						"wrapping": "word",
						"initially-visible": true,
						"origin": "top-left"
					},
					"uid": 15,
					"instanceVariables": {},
					"behaviors": {},
					"world": {
						"x": 736,
						"y": 699,
						"width": 200,
						"height": 30,
						"originX": 0,
						"originY": 0,
						"color": [
							1,
							1,
							1,
							1
						],
						"angle": 0,
						"zElevation": 0
					}
				},
				{
					"type": "showvalue",
					"properties": {
						"text": "Text",
						"enable-bbcode": true,
						"font": "Arial",
						"size": 12,
						"line-height": 0,
						"bold": false,
						"italic": false,
						"color": [
							0,
							0,
							0,
							1
						],
						"horizontal-alignment": "left",
						"vertical-alignment": "top",
						"wrapping": "word",
						"initially-visible": true,
						"origin": "top-left"
					},
					"uid": 18,
					"instanceVariables": {},
					"behaviors": {},
					"world": {
						"x": 589,
						"y": 574,
						"width": 149,
						"height": 49,
						"originX": 0,
						"originY": 0,
						"color": [
							1,
							1,
							1,
							1
						],
						"angle": 0,
						"zElevation": 0
					}
				},
				{
					"type": "Sprite7",
					"properties": {
						"initially-visible": true,
						"initial-animation": "Animation 1",
						"initial-frame": 0,
						"enable-collisions": true,
						"live-preview": false
					},
					"uid": 19,
					"instanceVariables": {},
					"behaviors": {
						"Pin": {
							"properties": {
								"destroy": true
							}
						}
					},
					"world": {
						"x": 430,
						"y": 696,
						"width": 103,
						"height": 40,
						"originX": 0,
						"originY": 0.5,
						"color": [
							1,
							1,
							1,
							1
						],
						"angle": 0,
						"zElevation": 0
					}
				},
				{
					"type": "movingValue",
					"properties": {
						"initially-visible": true,
						"initial-animation": "Animation 1",
						"initial-frame": 0,
						"enable-collisions": true,
						"live-preview": false
					},
					"uid": 20,
					"instanceVariables": {},
					"behaviors": {
						"Pin": {
							"properties": {
								"destroy": false
							}
						}
					},
					"world": {
						"x": 367.29359944882174,
						"y": 733.8966437973669,
						"width": 63.3739837398374,
						"height": 16,
						"originX": 0,
						"originY": 0.5,
						"color": [
							1,
							1,
							1,
							1
						],
						"angle": 0,
						"zElevation": 0
					}
				}
			],
			"sid": 473023660023609,
			"effectTypes": [],
			"isInitiallyVisible": true,
			"isInitiallyInteractive": true,
			"color": [
				1,
				1,
				1,
				1
			],
			"backgroundColor": [
				1,
				1,
				1,
				1
			],
			"isTransparent": false,
			"parallaxX": 1,
			"parallaxY": 1,
			"scaleRate": 1,
			"forceOwnTexture": false,
			"renderingMode": "3d",
			"drawOrder": "z-order",
			"useRenderCells": false,
			"blendMode": "normal",
			"zElevation": 0,
			"global": false
		}
	],
	"sid": 528302379216746,
	"nonworld-instances": [],
	"effectTypes": [],
	"width": 1708,
	"height": 960,
	"unboundedScrolling": false,
	"vpX": 0.5,
	"vpY": 0.5,
	"projection": "perspective",
	"eventSheet": "Event sheet 1"
}